fastapi_gae_logging/__init__.py
fastapi_gae_logging/fastapi_gae_logging.py
fastapi_gae_logging/py.typed
fastapi_gae_logging-0.1.0.dist-info/WHEEL
fastapi_gae_logging-0.1.0.dist-info/METADATA
fastapi_gae_logging-0.1.0.dist-info/RECORD
