Metadata-Version: 2.3
Name: fastapi-gae-logging
Version: 0.1.0
Summary: Custom Cloud Logging handler for FastAPI (or any Starlette based) applications deployed in Google App Engine. Groups logs coming from the same request lifecycle and propagates the maximum log level throughout the request lifecycle using middleware and context management.
Author: Chris Karvouniaris
Author-email: Chris Karvouniaris <christos.karvouniaris247@gmail.com>
License: MIT
Classifier: Programming Language :: Python :: 3
Classifier: Operating System :: OS Independent
Classifier: License :: OSI Approved :: MIT License
Requires-Dist: google-cloud-logging>=3.13.0
Requires-Dist: starlette>=0.49.3
Requires-Python: >=3.9
Project-URL: Homepage, https://github.com/chrisK824/fastapi-gae-logging
